goatpie/__init__.py
goatpie/app.py
goatpie/cli.py
goatpie/goatpie.py
goatpie/helpers.py
goatpie/components/__init__.py
goatpie/components/plotext.py
goatpie/components/widget.py
goatpie-0.4.0.dist-info/entry_points.txt
goatpie-0.4.0.dist-info/LICENSE
goatpie-0.4.0.dist-info/WHEEL
goatpie-0.4.0.dist-info/METADATA
goatpie-0.4.0.dist-info/RECORD
