Metadata-Version: 2.1
Name: goatpie
Version: 0.4.0
Summary: 'GoatCounter' analytics for the CLI, written in Python
Keywords: analytics,cli,goatcounter,privacy,tracking
Author-email: Martin Folkers <webmaster@refbw.de>
Requires-Python: >=3.7
Classifier: Programming Language :: Python :: 3
Classifier: License :: OSI Approved :: MIT License
Classifier: Operating System :: OS Independent
Requires-Dist: arrow
Requires-Dist: click
Requires-Dist: pandas
Requires-Dist: plotext
Requires-Dist: pycountry
Requires-Dist: requests
Requires-Dist: rich
Requires-Dist: textual
Requires-Dist: black==22.6.0 ; extra == "dev"
Requires-Dist: isort==5.10.1 ; extra == "dev"
Requires-Dist: pylint==2.15.0 ; extra == "dev"
Requires-Dist: pytest_cov==3.0.0 ; extra == "dev"
Project-URL: issues, https://codeberg.org/refbw/goatpie/issues
Project-URL: project, https://codeberg.org/refbw/goatpie
Provides-Extra: dev
